llm_cartographer/__init__.py
llm_cartographer/cli_navigator.py
llm_cartographer/codebase_navigator.py
llm_cartographer-0.1.1.dist-info/METADATA
llm_cartographer-0.1.1.dist-info/WHEEL
llm_cartographer-0.1.1.dist-info/entry_points.txt
llm_cartographer-0.1.1.dist-info/top_level.txt
llm_cartographer-0.1.1.dist-info/RECORD
