Metadata-Version: 2.2
Name: llm-cartographer
Version: 0.1.1
Summary: LLM plugin for automatically mapping and describing a codebase or project
Home-page: https://github.com/yourusername/llm-cartographer
Author: Thomas Thomas
Author-email: Thomas Thomas <irthomasthomas@gmail.com>
License: Apache-2.0
Requires-Python: >=3.9
Requires-Dist: llm>=0.5.0
Requires-Dist: click>=8.0.0
Requires-Dist: pathspec>=0.11.0
Requires-Dist: rich>=13.0.0
Requires-Dist: tqdm>=4.64.0
Requires-Dist: colorama>=0.4.6
Provides-Extra: test
Requires-Dist: pytest; extra == "test"
Requires-Dist: pytest-mock; extra == "test"
Dynamic: author
Dynamic: home-page
Dynamic: requires-python
